{"FullPath":"D:\\UnityHub\\2017.4.34f1\\Editor\\Data\\PlaybackEngines\\MetroSupport\\Players\\UAP\\dotnet\\x86\\Release\\UnityEngineDelegates.winmd","InProcServers":{"UnityEngineDelegates.dll":{"Path":"UnityEngineDelegates.dll","TypeToThreadingModel":{"UnityEngineDelegates.FunctionDefsDictionary":"both"}}},"Namespaces":{"UnityEngineDelegates.FunctionDefsDictionary":"UnityEngineDelegates","UnityEngineDelegates.__IFunctionDefsDictionaryPublicNonVirtuals":"UnityEngineDelegates","UnityEngineDelegates.__IFunctionDefsDictionaryStatics":"UnityEngineDelegates"},"RootNamespace":"UnityEngineDelegates","AssemblyVersion":"16.0.29311.281"}